Metadata-Version: 2.1
Name: rubikmathik
Version: 0.0.2
Summary: Calculador de cubos de lados cuadrados y rectangulares
Home-page: https://github.com/Wladimir3984/rubikmathik
Author: Wladimir Urzúa Calderón
License: GNU GENERAL PUBLIC LICENSE
License-File: LICENSE
